kcrawler/Boss.py
kcrawler/__init__.py
kcrawler/cli.py
kcrawler/anjuke/__init__.py
kcrawler/anjuke/community.py
kcrawler/core/Crawler.py
kcrawler/core/__init__.py
kcrawler/juejin/__init__.py
kcrawler/juejin/books.py
kcrawler/juejin/posts.py
kcrawler/juejin/urlparser.py
kcrawler-1.1.dist-info/LICENSE
kcrawler-1.1.dist-info/METADATA
kcrawler-1.1.dist-info/WHEEL
kcrawler-1.1.dist-info/entry_points.txt
kcrawler-1.1.dist-info/top_level.txt
kcrawler-1.1.dist-info/RECORD
