Metadata-Version: 2.1
Name: kcrawler
Version: 1.1
Summary: A python crawler authored by Ken.
Home-page: https://github.com/kenblikylee/kcrawler
Author: ken
Author-email: kenbliky@gmail.com
License: MIT
Platform: UNKNOWN
Classifier: Programming Language :: Python :: 3
Classifier: License :: OSI Approved :: MIT License
Classifier: Operating System :: OS Independent
Requires-Python: >=3.6
Requires-Dist: requests (>=2.21.0)
Requires-Dist: beautifulsoup4 (>=4.7.1)
Requires-Dist: pandas (>=0.25.1)
Requires-Dist: matplotlib (>=3.0.3)
Requires-Dist: xlwt (>=1.3.0)
Requires-Dist: Pillow (>=6.1.0)
